economic_term-0.2.0.dist-info/METADATA
economic_term-0.2.0.dist-info/WHEEL
economic_term/__init__.py
economic_term-0.2.0.dist-info/RECORD
